getmanga/__init__.py
getmanga/loader/__init__.py
getmanga/loader/mridecoder.py
getmanga/parsers/__init__.py
getmanga/parsers/mangalib.py
getmanga/parsers/mangarock.py
getmanga-0.1.7.dist-info/LICENSE
getmanga-0.1.7.dist-info/METADATA
getmanga-0.1.7.dist-info/WHEEL
getmanga-0.1.7.dist-info/top_level.txt
getmanga-0.1.7.dist-info/RECORD
