Metadata-Version: 2.1
Name: getmanga
Version: 0.1.7
Summary: package for load manga! :)
Home-page: https://github.com/Tynukua/getManga
Author: Tynukua
Author-email: tynuk.ua@gmail.com
License: UNKNOWN
Platform: UNKNOWN
Classifier: Programming Language :: Python :: 3.7
Classifier: License :: OSI Approved :: MIT License
Classifier: Operating System :: OS Independent
Requires-Dist: aiohttp
Requires-Dist: requests
Requires-Dist: beautifulsoup4
Requires-Dist: aiofiles
